qicore/__init__.py
qicore/linux/lib/libqicore.so
qicore/linux/share/qi/module/qicore.mod
qicore-2.0.0.dist-info/DESCRIPTION.rst
qicore-2.0.0.dist-info/LICENSE.txt
qicore-2.0.0.dist-info/METADATA
qicore-2.0.0.dist-info/RECORD
qicore-2.0.0.dist-info/WHEEL
qicore-2.0.0.dist-info/metadata.json
qicore-2.0.0.dist-info/top_level.txt
