Metadata-Version: 2.0
Name: qicore
Version: 2.0.0
Summary: QiCore Python Module
Home-page: http://doc.aldebaran.com
Author: SoftBank Robotics
Author-email: release@softbankrobotics.com
License: UNKNOWN
Keywords: naoqi softbank nao pepper romeo robot
Platform: manylinux1-x86_64
Classifier: Development Status :: 5 - Production/Stable
Classifier: Intended Audience :: Developers
Classifier: Topic :: Software Development :: Embedded Systems
Classifier: Framework :: Robot Framework :: Tool
Classifier: Programming Language :: Python :: 2
Classifier: Operating System :: POSIX :: Linux
Requires-Python: >=2.6, <3
Requires-Dist: qi
